<annotation>
	<folder>my_data</folder>
	<filename>72.jpg</filename>
	<path>/home/river/PycharmProjects/yolov5/pythonProject/yolo_v5/my_data/72.jpg</path>
	<source>
		<database>Unknown</database>
	</source>
	<size>
		<width>1280</width>
		<height>960</height>
		<depth>3</depth>
	</size>
	<segmented>0</segmented>
	<object>
		<name>person</name>
		<pose>Unspecified</pose>
		<truncated>0</truncated>
		<difficult>0</difficult>
		<bndbox>
			<xmin>592</xmin>
			<ymin>452</ymin>
			<xmax>767</xmax>
			<ymax>760</ymax>
		</bndbox>
	</object>
	<object>
		<name>person</name>
		<pose>Unspecified</pose>
		<truncated>0</truncated>
		<difficult>0</difficult>
		<bndbox>
			<xmin>153</xmin>
			<ymin>447</ymin>
			<xmax>241</xmax>
			<ymax>594</ymax>
		</bndbox>
	</object>
	<object>
		<name>person</name>
		<pose>Unspecified</pose>
		<truncated>0</truncated>
		<difficult>0</difficult>
		<bndbox>
			<xmin>532</xmin>
			<ymin>446</ymin>
			<xmax>599</xmax>
			<ymax>635</ymax>
		</bndbox>
	</object>
</annotation>
