<annotation>
	<folder>image</folder>
	<filename>person-59.jpg</filename>
	<path>C:\Users\h1412\Documents\yolo_v5\训练集\image\person-59.jpg</path>
	<source>
		<database>Unknown</database>
	</source>
	<size>
		<width>1440</width>
		<height>1920</height>
		<depth>3</depth>
	</size>
	<segmented>0</segmented>
	<object>
		<name>person</name>
		<pose>Unspecified</pose>
		<truncated>0</truncated>
		<difficult>0</difficult>
		<bndbox>
			<xmin>711</xmin>
			<ymin>620</ymin>
			<xmax>984</xmax>
			<ymax>1297</ymax>
		</bndbox>
	</object>
	<object>
		<name>phone</name>
		<pose>Unspecified</pose>
		<truncated>0</truncated>
		<difficult>0</difficult>
		<bndbox>
			<xmin>715</xmin>
			<ymin>807</ymin>
			<xmax>798</xmax>
			<ymax>853</ymax>
		</bndbox>
	</object>
</annotation>
