<annotation>
	<folder>image</folder>
	<filename>person-108.jpg</filename>
	<path>C:\Users\h1412\Documents\yolo_v5\训练集\image\person-108.jpg</path>
	<source>
		<database>Unknown</database>
	</source>
	<size>
		<width>1440</width>
		<height>1080</height>
		<depth>3</depth>
	</size>
	<segmented>0</segmented>
	<object>
		<name>person</name>
		<pose>Unspecified</pose>
		<truncated>1</truncated>
		<difficult>0</difficult>
		<bndbox>
			<xmin>617</xmin>
			<ymin>216</ymin>
			<xmax>935</xmax>
			<ymax>1080</ymax>
		</bndbox>
	</object>
	<object>
		<name>phone</name>
		<pose>Unspecified</pose>
		<truncated>0</truncated>
		<difficult>0</difficult>
		<bndbox>
			<xmin>674</xmin>
			<ymin>451</ymin>
			<xmax>797</xmax>
			<ymax>545</ymax>
		</bndbox>
	</object>
</annotation>
